GOFindBias-1.2.3b1.dist-info/DESCRIPTION.rst
GOFindBias-1.2.3b1.dist-info/METADATA
GOFindBias-1.2.3b1.dist-info/RECORD
GOFindBias-1.2.3b1.dist-info/WHEEL
GOFindBias-1.2.3b1.dist-info/entry_points.txt
GOFindBias-1.2.3b1.dist-info/metadata.json
GOFindBias-1.2.3b1.dist-info/top_level.txt
lib/GOFindBias.py
lib/__init__.py
