Metadata-Version: 2.0
Name: GOFindBias
Version: 1.2.3b1
Summary: Analysis of the .gaf files for futher debias analysis.
Home-page: https://github.com/Pranavkhade/GOFindBias
Author: Pranav Khade
Author-email: pranavk@iastate.edu
License: UNKNOWN
Keywords: GO Annotation
Platform: UNKNOWN
Classifier: Development Status :: 4 - Beta
Classifier: Intended Audience :: Developers
Classifier: Topic :: Software Development :: Build Tools
Classifier: License :: OSI Approved :: GNU General Public License v3 (GPLv3)
Classifier: Programming Language :: Python :: 2.7
Requires-Dist: Biopython
Requires-Dist: matplotlib
